sqlidps/__init__.py
sqlidps/inference.py
sqlidps/lex.yy.c
sqlidps/model.npz
sqlidps/sql_tokenizer.cpython-39-darwin.so
sqlidps/wrapper.c
sqlidps/wrapper.h
sqlidps-1.2.1.dist-info/licenses/LICENSE
sqlidps-1.2.1.dist-info/METADATA
sqlidps-1.2.1.dist-info/WHEEL
sqlidps-1.2.1.dist-info/top_level.txt
sqlidps-1.2.1.dist-info/RECORD
