Metadata-Version: 2.4
Name: sqlidps
Version: 1.2.1
Summary: A simple SQL-injection detector based on ML
Home-page: https://github.com/DPRIYATHAM/sqlidps/
Author: Darisi Priyatham, Arjun Manjunath
Author-email: priyathamdarisi@gmail.com, dev.arjunmnath@gmail.com
Maintainer: Arjun Manjunath
Maintainer-email: dev.arjunmnath@gmail.com
Project-URL: Bug Reports, https://github.com/DPRIYATHAM/sqlidps/issues
Project-URL: Source, https://github.com/DPRIYATHAM/sqlidps/
Keywords: sql injection detection security machine-learning
Classifier: Intended Audience :: Developers
Classifier: Programming Language :: Python :: 3
Classifier: Programming Language :: Python :: 3.8
Classifier: Programming Language :: Python :: 3.9
Classifier: Programming Language :: Python :: 3.10
Classifier: Programming Language :: Python :: 3.11
Classifier: Programming Language :: Python :: 3.12
Classifier: Programming Language :: C
Classifier: License :: OSI Approved :: MIT License
Classifier: Operating System :: POSIX :: Linux
Classifier: Operating System :: MacOS
Classifier: Operating System :: Microsoft :: Windows
Classifier: Topic :: Software Development :: Libraries :: Python Modules
Classifier: Topic :: Security
Requires-Python: >=3.8
License-File: LICENSE
Requires-Dist: numpy
Dynamic: author
Dynamic: author-email
Dynamic: classifier
Dynamic: description
Dynamic: description-content-type
Dynamic: home-page
Dynamic: keywords
Dynamic: license-file
Dynamic: maintainer
Dynamic: maintainer-email
Dynamic: project-url
Dynamic: requires-dist
Dynamic: requires-python
Dynamic: summary
